ai_executor/__init__.py
ai_executor-0.2.7.dist-info/METADATA
ai_executor-0.2.7.dist-info/WHEEL
ai_executor-0.2.7.dist-info/top_level.txt
ai_executor-0.2.7.dist-info/RECORD
