Metadata-Version: 2.1
Name: ai-executor
Version: 0.2.7
Summary: A Python package for executing methods generated by ChatGPT
Home-page: https://github.com/ZS520L/LegoAI-by-AUST
Author: LegoAI
Author-email: li17719333702@gmail.com
Requires-Dist: openai
